{
  "books": [
    {
      "id": 2,
      "title": "Negeri 5 Menara",
      "author": "Ahmad Fuadi",
      "year": 2009,
      "quantity": 5
    },
    {
      "id": 3,
      "title": "Dilan: Dia adalah Dilanku Tahun 1990",
      "author": "Pidi Baiq",
      "year": 2014,
      "quantity": 2
    },
    {
      "title": "Bumi Manusia",
      "author": "Pramoedya Ananta Toer",
      "year": "1980",
      "quantity": "43",
      "id": 5
    },
    {
      "title": "Laut Bercermin",
      "author": "Remy Sylado",
      "year": "1994",
      "quantity": "112",
      "id": 6
    },
    {
      "id": 7,
      "title": "Sang Pemimpi",
      "author": "Andrea Hirata",
      "year": 2006,
      "quantity": 6
    }
  ]
}